humble_explorer/__init__.py
humble_explorer/__main__.py
humble_explorer/app.css
humble_explorer/app.py
humble_explorer/renderables.py
humble_explorer/utils.py
humble_explorer/widgets.py
humble_explorer-0.5.0.dist-info/LICENSE.txt
humble_explorer-0.5.0.dist-info/METADATA
humble_explorer-0.5.0.dist-info/WHEEL
humble_explorer-0.5.0.dist-info/entry_points.txt
humble_explorer-0.5.0.dist-info/top_level.txt
humble_explorer-0.5.0.dist-info/RECORD
