Metadata-Version: 2.1
Name: humble-explorer
Version: 0.5.0
Summary: Cross-platform, command-line and human-friendly Bluetooth Low Energy Explorer
Home-page: https://github.com/koenvervloesem/humble-explorer/
Author: Koen Vervloesem
Author-email: koen@vervloesem.eu
License: MIT
Project-URL: Documentation, https://humble-explorer.readthedocs.io/
Project-URL: Source, https://github.com/koenvervloesem/humble-explorer/
Project-URL: Changelog, https://github.com/koenvervloesem/humble-explorer/blob/main/CHANGELOG.rst
Project-URL: Tracker, https://github.com/koenvervloesem/humble-explorer/issues
Project-URL: Download, https://pypi.org/project/humble-explorer/#files
Platform: any
Classifier: Development Status :: 4 - Beta
Classifier: Environment :: Console
Classifier: License :: OSI Approved :: MIT License
Classifier: Operating System :: MacOS
Classifier: Operating System :: Microsoft :: Windows
Classifier: Operating System :: POSIX :: Linux
Classifier: Programming Language :: Python :: 3.7
Classifier: Programming Language :: Python :: 3.8
Classifier: Programming Language :: Python :: 3.9
Classifier: Programming Language :: Python :: 3.10
Classifier: Programming Language :: Python :: 3.11
Classifier: Topic :: Utilities
License-File: LICENSE.txt
Requires-Dist: bluetooth-numbers (<2.0,>=1.0.0)
Requires-Dist: bleak (>=0.20.0)
Requires-Dist: textual (>=0.14.0)
Requires-Dist: importlib-metadata ; python_version < "3.8"
Provides-Extra: testing
Requires-Dist: pytest ; extra == 'testing'
Requires-Dist: pytest-cov ; extra == 'testing'
Requires-Dist: setuptools ; extra == 'testing'
Requires-Dist: textual[dev] (>=0.14.0) ; extra == 'testing'
